dftt_timecode/__init__.py
dftt_timecode/dispatch.py
dftt_timecode/error.py
dftt_timecode/pattern.py
dftt_timecode/core/dftt_timecode.py
dftt_timecode-0.0.14.dist-info/LICENSE
dftt_timecode-0.0.14.dist-info/METADATA
dftt_timecode-0.0.14.dist-info/WHEEL
dftt_timecode-0.0.14.dist-info/top_level.txt
dftt_timecode-0.0.14.dist-info/RECORD
