Metadata-Version: 2.1
Name: dftt_timecode
Version: 0.0.14
Summary: Timecode library for film and TV industry, supports HFR and a bunch of cool features
Home-page: https://github.com/OwenYou/dftt_timecode
Author: You Ziyuan
Author-email: hikaridragon0216@gmail.com
Classifier: Programming Language :: Python :: 3
Classifier: Development Status :: 2 - Pre-Alpha
Classifier: License :: OSI Approved :: GNU Lesser General Public License v2 (LGPLv2)
Classifier: Natural Language :: Chinese (Simplified)
Classifier: Operating System :: OS Independent
Requires-Python: >=3.10
License-File: LICENSE
